<?xml version="1.0" encoding="UTF-8"?>
<PeakList>
  <PeakList1D>
    <PeakList1DHeader creator="nmr" date="2020-12-08T04:12:57.084-08:00" expNo="2" name="drydown_159" owner="" procNo="1" source="C:/Bruker/TopSpin3.6.0/data/sfansler/nmr">
      <PeakPickDetails>F1=16.265169ppm, F2=-3.760375ppm, MI=0.10cm, MAXI=10000.00cm, PC=1.000
      </PeakPickDetails>
    </PeakList1DHeader>
    <Peak1D F1="8.446810" intensity="9.200294e+000" type="0"/>
    <Peak1D F1="6.919907" intensity="1.056604e-001" type="0"/>
    <Peak1D F1="5.996020" intensity="1.290472e-001" type="0"/>
    <Peak1D F1="5.901961" intensity="1.011318e-001" type="0"/>
    <Peak1D F1="5.802603" intensity="1.323377e-001" type="0"/>
    <Peak1D F1="5.782899" intensity="1.503982e-001" type="0"/>
    <Peak1D F1="5.763075" intensity="1.146748e-001" type="0"/>
    <Peak1D F1="5.750845" intensity="1.055845e-001" type="0"/>
    <Peak1D F1="5.737019" intensity="1.045461e-001" type="0"/>
    <Peak1D F1="5.702092" intensity="1.097743e-001" type="0"/>
    <Peak1D F1="5.642422" intensity="1.293316e-001" type="0"/>
    <Peak1D F1="5.624555" intensity="1.460756e-001" type="0"/>
    <Peak1D F1="5.614436" intensity="1.431661e-001" type="0"/>
    <Peak1D F1="5.608296" intensity="1.448935e-001" type="0"/>
    <Peak1D F1="5.598046" intensity="1.513047e-001" type="0"/>
    <Peak1D F1="5.442132" intensity="3.691406e-001" type="0"/>
    <Peak1D F1="5.433400" intensity="3.660824e-001" type="0"/>
    <Peak1D F1="5.410625" intensity="3.743806e-001" type="0"/>
    <Peak1D F1="5.401427" intensity="4.453477e-001" type="0"/>
    <Peak1D F1="5.389098" intensity="4.098227e-001" type="0"/>
    <Peak1D F1="5.380249" intensity="3.488553e-001" type="0"/>
    <Peak1D F1="5.316668" intensity="3.292621e-001" type="0"/>
    <Peak1D F1="5.279576" intensity="3.734953e-001" type="0"/>
    <Peak1D F1="5.260624" intensity="3.873042e-001" type="0"/>
    <Peak1D F1="5.228059" intensity="1.103004e+000" type="0"/>
    <Peak1D F1="5.218675" intensity="1.137098e+000" type="0"/>
    <Peak1D F1="5.209450" intensity="7.181450e-001" type="0"/>
    <Peak1D F1="5.192122" intensity="4.430301e+000" type="0"/>
    <Peak1D F1="5.182594" intensity="4.201164e+000" type="0"/>
    <Peak1D F1="5.158212" intensity="4.344210e-001" type="0"/>
    <Peak1D F1="5.133274" intensity="4.814177e-001" type="0"/>
    <Peak1D F1="5.118002" intensity="5.949180e-001" type="0"/>
    <Peak1D F1="5.108127" intensity="6.097248e-001" type="0"/>
    <Peak1D F1="5.088771" intensity="5.917591e-001" type="0"/>
    <Peak1D F1="5.074446" intensity="5.820313e-001" type="0"/>
    <Peak1D F1="5.055398" intensity="6.560416e-001" type="0"/>
    <Peak1D F1="5.041392" intensity="7.379586e-001" type="0"/>
    <Peak1D F1="4.963017" intensity="1.072540e+000" type="0"/>
    <Peak1D F1="4.953976" intensity="1.087668e+000" type="0"/>
    <Peak1D F1="4.901608" intensity="1.769717e+000" type="0"/>
    <Peak1D F1="4.883233" intensity="1.987491e+000" type="0"/>
    <Peak1D F1="4.782872" intensity="2.821667e+003" type="0"/>
    <Peak1D F1="4.646145" intensity="5.197617e-001" type="0"/>
    <Peak1D F1="4.626294" intensity="5.940045e-001" type="0"/>
    <Peak1D F1="4.228771" intensity="1.064259e-001" type="0"/>
    <Peak1D F1="4.219334" intensity="1.127018e-001" type="0"/>
    <Peak1D F1="4.210127" intensity="1.212777e-001" type="0"/>
    <Peak1D F1="4.197494" intensity="1.496174e-001" type="0"/>
    <Peak1D F1="4.180346" intensity="1.600518e-001" type="0"/>
    <Peak1D F1="4.164446" intensity="3.395158e-001" type="0"/>
    <Peak1D F1="4.148686" intensity="4.827543e-001" type="0"/>
    <Peak1D F1="4.132373" intensity="5.046333e-001" type="0"/>
    <Peak1D F1="4.126927" intensity="3.621480e-001" type="0"/>
    <Peak1D F1="4.116591" intensity="4.653294e-001" type="0"/>
    <Peak1D F1="4.109644" intensity="3.126177e-001" type="0"/>
    <Peak1D F1="4.099731" intensity="2.678109e-001" type="0"/>
    <Peak1D F1="4.091750" intensity="3.362675e-001" type="0"/>
    <Peak1D F1="4.083408" intensity="3.128543e-001" type="0"/>
    <Peak1D F1="4.075894" intensity="3.538915e-001" type="0"/>
    <Peak1D F1="4.069700" intensity="3.439855e-001" type="0"/>
    <Peak1D F1="4.060786" intensity="3.604436e-001" type="0"/>
    <Peak1D F1="4.051538" intensity="3.367117e-001" type="0"/>
    <Peak1D F1="4.045145" intensity="3.522733e-001" type="0"/>
    <Peak1D F1="4.032512" intensity="4.157397e-001" type="0"/>
    <Peak1D F1="4.009812" intensity="5.448440e-001" type="0"/>
    <Peak1D F1="3.998815" intensity="5.699192e-001" type="0"/>
    <Peak1D F1="3.986387" intensity="6.798577e-001" type="0"/>
    <Peak1D F1="3.970770" intensity="9.993663e-001" type="0"/>
    <Peak1D F1="3.962649" intensity="9.387442e-001" type="0"/>
    <Peak1D F1="3.940668" intensity="1.376116e+000" type="0"/>
    <Peak1D F1="3.929675" intensity="2.538381e+000" type="0"/>
    <Peak1D F1="3.905485" intensity="1.669056e+000" type="0"/>
    <Peak1D F1="3.900548" intensity="1.471344e+000" type="0"/>
    <Peak1D F1="3.892656" intensity="1.200826e+000" type="0"/>
    <Peak1D F1="3.871715" intensity="4.304218e+000" type="0"/>
    <Peak1D F1="3.866147" intensity="3.002619e+000" type="0"/>
    <Peak1D F1="3.848541" intensity="5.161290e+000" type="0"/>
    <Peak1D F1="3.836942" intensity="6.083932e+000" type="0"/>
    <Peak1D F1="3.825457" intensity="5.451503e+000" type="0"/>
    <Peak1D F1="3.820515" intensity="3.602590e+000" type="0"/>
    <Peak1D F1="3.813873" intensity="3.151360e+000" type="0"/>
    <Peak1D F1="3.801210" intensity="3.391757e+000" type="0"/>
    <Peak1D F1="3.796858" intensity="3.034958e+000" type="0"/>
    <Peak1D F1="3.781729" intensity="3.362374e+000" type="0"/>
    <Peak1D F1="3.774082" intensity="4.152805e+000" type="0"/>
    <Peak1D F1="3.761985" intensity="4.099896e+000" type="0"/>
    <Peak1D F1="3.744613" intensity="3.626311e+000" type="0"/>
    <Peak1D F1="3.734082" intensity="2.815478e+000" type="0"/>
    <Peak1D F1="3.720917" intensity="1.936558e+000" type="0"/>
    <Peak1D F1="3.704621" intensity="1.853671e+000" type="0"/>
    <Peak1D F1="3.689074" intensity="1.791931e+000" type="0"/>
    <Peak1D F1="3.681517" intensity="1.307107e+000" type="0"/>
    <Peak1D F1="3.673482" intensity="1.259000e+000" type="0"/>
    <Peak1D F1="3.656939" intensity="3.777007e+000" type="0"/>
    <Peak1D F1="3.647195" intensity="3.499644e+000" type="0"/>
    <Peak1D F1="3.632101" intensity="3.333035e+000" type="0"/>
    <Peak1D F1="3.622331" intensity="3.332136e+000" type="0"/>
    <Peak1D F1="3.589530" intensity="1.293418e+000" type="0"/>
    <Peak1D F1="3.569796" intensity="1.481803e+000" type="0"/>
    <Peak1D F1="3.553896" intensity="1.143064e+000" type="0"/>
    <Peak1D F1="3.547396" intensity="1.063450e+000" type="0"/>
    <Peak1D F1="3.541099" intensity="1.456579e+000" type="0"/>
    <Peak1D F1="3.531737" intensity="1.278897e+000" type="0"/>
    <Peak1D F1="3.523972" intensity="1.145923e+000" type="0"/>
    <Peak1D F1="3.516661" intensity="1.427888e+000" type="0"/>
    <Peak1D F1="3.503931" intensity="1.831561e+000" type="0"/>
    <Peak1D F1="3.481331" intensity="2.085766e+000" type="0"/>
    <Peak1D F1="3.464859" intensity="2.856476e+000" type="0"/>
    <Peak1D F1="3.458751" intensity="1.957983e+000" type="0"/>
    <Peak1D F1="3.450247" intensity="1.326353e+000" type="0"/>
    <Peak1D F1="3.441556" intensity="4.280564e+000" type="0"/>
    <Peak1D F1="3.424157" intensity="1.075188e+000" type="0"/>
    <Peak1D F1="3.418128" intensity="2.183083e+000" type="0"/>
    <Peak1D F1="3.412901" intensity="1.891906e+000" type="0"/>
    <Peak1D F1="3.401174" intensity="1.057970e+000" type="0"/>
    <Peak1D F1="3.389735" intensity="1.097106e+000" type="0"/>
    <Peak1D F1="3.377990" intensity="5.919213e-001" type="0"/>
    <Peak1D F1="3.366263" intensity="5.676205e-001" type="0"/>
    <Peak1D F1="3.356844" intensity="3.075317e-001" type="0"/>
    <Peak1D F1="3.345268" intensity="4.232696e-001" type="0"/>
    <Peak1D F1="3.324347" intensity="2.094651e-001" type="0"/>
    <Peak1D F1="3.312639" intensity="1.757452e-001" type="0"/>
    <Peak1D F1="3.290784" intensity="2.072981e-001" type="0"/>
    <Peak1D F1="3.282895" intensity="1.933579e-001" type="0"/>
    <Peak1D F1="3.267383" intensity="2.651792e-001" type="0"/>
    <Peak1D F1="3.256269" intensity="1.575219e+000" type="0"/>
    <Peak1D F1="3.235617" intensity="7.532089e-001" type="0"/>
    <Peak1D F1="3.220253" intensity="5.330381e-001" type="0"/>
    <Peak1D F1="3.213618" intensity="6.074963e-001" type="0"/>
    <Peak1D F1="3.192648" intensity="3.110041e-001" type="0"/>
    <Peak1D F1="2.804343" intensity="2.418534e-001" type="0"/>
    <Peak1D F1="2.766307" intensity="1.337156e-001" type="0"/>
    <Peak1D F1="2.745540" intensity="1.009484e-001" type="0"/>
    <Peak1D F1="2.483928" intensity="1.187424e-001" type="0"/>
    <Peak1D F1="2.469535" intensity="1.075179e-001" type="0"/>
    <Peak1D F1="2.440815" intensity="1.144163e-001" type="0"/>
    <Peak1D F1="2.428783" intensity="2.618006e-001" type="0"/>
    <Peak1D F1="2.424250" intensity="2.120406e-001" type="0"/>
    <Peak1D F1="2.411119" intensity="4.153391e-001" type="0"/>
    <Peak1D F1="2.393510" intensity="1.830779e+000" type="0"/>
    <Peak1D F1="2.374863" intensity="5.868666e-001" type="0"/>
    <Peak1D F1="2.364238" intensity="2.777331e-001" type="0"/>
    <Peak1D F1="2.359399" intensity="2.695487e-001" type="0"/>
    <Peak1D F1="2.341072" intensity="4.308242e-001" type="0"/>
    <Peak1D F1="2.323555" intensity="3.748981e-001" type="0"/>
    <Peak1D F1="2.316586" intensity="5.425270e-001" type="0"/>
    <Peak1D F1="2.300478" intensity="5.343800e-001" type="0"/>
    <Peak1D F1="2.288130" intensity="2.110138e-001" type="0"/>
    <Peak1D F1="2.280590" intensity="3.319758e-001" type="0"/>
    <Peak1D F1="2.268593" intensity="2.649376e-001" type="0"/>
    <Peak1D F1="2.264624" intensity="3.157054e-001" type="0"/>
    <Peak1D F1="2.253802" intensity="1.331229e-001" type="0"/>
    <Peak1D F1="2.241311" intensity="2.114949e-001" type="0"/>
    <Peak1D F1="2.220204" intensity="2.296820e-001" type="0"/>
    <Peak1D F1="2.212793" intensity="5.105554e-001" type="0"/>
    <Peak1D F1="2.200561" intensity="2.454097e-001" type="0"/>
    <Peak1D F1="2.179811" intensity="2.862877e-001" type="0"/>
    <Peak1D F1="2.161908" intensity="3.588555e-001" type="0"/>
    <Peak1D F1="2.143507" intensity="3.033887e-001" type="0"/>
    <Peak1D F1="2.131210" intensity="2.368748e-001" type="0"/>
    <Peak1D F1="2.126395" intensity="2.411209e-001" type="0"/>
    <Peak1D F1="2.119896" intensity="2.368521e-001" type="0"/>
    <Peak1D F1="2.112566" intensity="2.524536e-001" type="0"/>
    <Peak1D F1="2.100669" intensity="2.609221e-001" type="0"/>
    <Peak1D F1="2.089967" intensity="2.626919e-001" type="0"/>
    <Peak1D F1="2.080967" intensity="2.421159e-001" type="0"/>
    <Peak1D F1="2.071434" intensity="3.558350e-001" type="0"/>
    <Peak1D F1="2.063147" intensity="3.844604e-001" type="0"/>
    <Peak1D F1="2.054596" intensity="5.937933e-001" type="0"/>
    <Peak1D F1="2.043096" intensity="4.677195e-001" type="0"/>
    <Peak1D F1="2.035403" intensity="4.821932e-001" type="0"/>
    <Peak1D F1="2.028502" intensity="3.874973e-001" type="0"/>
    <Peak1D F1="2.015717" intensity="2.951486e-001" type="0"/>
    <Peak1D F1="2.001472" intensity="2.395312e-001" type="0"/>
    <Peak1D F1="1.992078" intensity="2.639692e-001" type="0"/>
    <Peak1D F1="1.979248" intensity="3.043364e-001" type="0"/>
    <Peak1D F1="1.971898" intensity="2.124428e-001" type="0"/>
    <Peak1D F1="1.906236" intensity="1.500000e+001" type="0"/>
    <Peak1D F1="1.894269" intensity="7.845489e-001" type="0"/>
    <Peak1D F1="1.888811" intensity="7.774551e-001" type="0"/>
    <Peak1D F1="1.880716" intensity="4.273826e-001" type="0"/>
    <Peak1D F1="1.875304" intensity="3.675357e-001" type="0"/>
    <Peak1D F1="1.858216" intensity="3.498808e-001" type="0"/>
    <Peak1D F1="1.818784" intensity="1.392394e-001" type="0"/>
    <Peak1D F1="1.803004" intensity="1.377580e-001" type="0"/>
    <Peak1D F1="1.782389" intensity="1.403531e-001" type="0"/>
    <Peak1D F1="1.764853" intensity="1.252217e-001" type="0"/>
    <Peak1D F1="1.745785" intensity="1.860079e-001" type="0"/>
    <Peak1D F1="1.716582" intensity="1.486571e-001" type="0"/>
    <Peak1D F1="1.699476" intensity="1.549712e-001" type="0"/>
    <Peak1D F1="1.670100" intensity="1.163539e-001" type="0"/>
    <Peak1D F1="1.660758" intensity="1.018407e-001" type="0"/>
    <Peak1D F1="1.642419" intensity="1.007688e-001" type="0"/>
    <Peak1D F1="1.618045" intensity="1.031904e-001" type="0"/>
    <Peak1D F1="1.571816" intensity="1.424712e-001" type="0"/>
    <Peak1D F1="1.552166" intensity="1.843620e-001" type="0"/>
    <Peak1D F1="1.536764" intensity="2.395572e-001" type="0"/>
    <Peak1D F1="1.518852" intensity="2.112962e-001" type="0"/>
    <Peak1D F1="1.478775" intensity="6.552063e-001" type="0"/>
    <Peak1D F1="1.460662" intensity="7.245570e-001" type="0"/>
    <Peak1D F1="1.435436" intensity="1.893058e-001" type="0"/>
    <Peak1D F1="1.414829" intensity="1.931601e-001" type="0"/>
    <Peak1D F1="1.389812" intensity="2.169929e-001" type="0"/>
    <Peak1D F1="1.359595" intensity="2.614720e-001" type="0"/>
    <Peak1D F1="1.344996" intensity="3.335771e-001" type="0"/>
    <Peak1D F1="1.337721" intensity="3.002574e-001" type="0"/>
    <Peak1D F1="1.326863" intensity="8.601690e-001" type="0"/>
    <Peak1D F1="1.309765" intensity="9.555193e-001" type="0"/>
    <Peak1D F1="1.290285" intensity="6.074299e-001" type="0"/>
    <Peak1D F1="1.258534" intensity="5.081351e-001" type="0"/>
    <Peak1D F1="1.221969" intensity="3.261068e-001" type="0"/>
    <Peak1D F1="1.196978" intensity="1.968780e+000" type="0"/>
    <Peak1D F1="1.181292" intensity="1.991818e+000" type="0"/>
    <Peak1D F1="1.155193" intensity="3.537854e-001" type="0"/>
    <Peak1D F1="1.123351" intensity="2.489965e-001" type="0"/>
    <Peak1D F1="1.106729" intensity="2.008585e-001" type="0"/>
    <Peak1D F1="1.099136" intensity="1.993074e-001" type="0"/>
    <Peak1D F1="1.082316" intensity="1.768328e-001" type="0"/>
    <Peak1D F1="1.065913" intensity="1.534712e-001" type="0"/>
    <Peak1D F1="1.061049" intensity="1.542166e-001" type="0"/>
    <Peak1D F1="1.052569" intensity="1.161903e-001" type="0"/>
    <Peak1D F1="1.041759" intensity="3.679368e-001" type="0"/>
    <Peak1D F1="1.024021" intensity="3.582402e-001" type="0"/>
    <Peak1D F1="1.009196" intensity="2.198731e-001" type="0"/>
    <Peak1D F1="0.990341" intensity="4.206319e-001" type="0"/>
    <Peak1D F1="0.972489" intensity="3.806235e-001" type="0"/>
    <Peak1D F1="0.964676" intensity="3.347036e-001" type="0"/>
    <Peak1D F1="0.949058" intensity="5.156274e-001" type="0"/>
    <Peak1D F1="0.937503" intensity="5.413111e-001" type="0"/>
    <Peak1D F1="0.930043" intensity="4.624041e-001" type="0"/>
    <Peak1D F1="0.920620" intensity="4.530966e-001" type="0"/>
    <Peak1D F1="0.911932" intensity="4.001014e-001" type="0"/>
    <Peak1D F1="0.901871" intensity="3.587055e-001" type="0"/>
    <Peak1D F1="0.893017" intensity="3.407595e-001" type="0"/>
    <Peak1D F1="0.884256" intensity="3.873112e-001" type="0"/>
    <Peak1D F1="0.872304" intensity="3.211643e-001" type="0"/>
    <Peak1D F1="0.865352" intensity="3.189621e-001" type="0"/>
    <Peak1D F1="-0.000148" intensity="2.499564e+001" type="0"/>
    <Peak1D F1="-0.149739" intensity="1.944751e-001" type="0"/>
  </PeakList1D>
</PeakList>
